README.md
setup.py
venvfix.py
venvfix.egg-info/PKG-INFO
venvfix.egg-info/SOURCES.txt
venvfix.egg-info/dependency_links.txt
venvfix.egg-info/entry_points.txt
venvfix.egg-info/top_level.txt