Metadata-Version: 2.2
Name: venvfix
Version: 0.3.6
Summary: A python script to fix venv after moved or renamed
Home-page: https://github.com/ci-ke/venv-fix
Author: cike
License: MIT Licence
Keywords: venv,fix
Requires-Python: >=3.5
Dynamic: author
Dynamic: description
Dynamic: home-page
Dynamic: keywords
Dynamic: license
Dynamic: requires-python
Dynamic: summary
